rikki/__init__.py
rikki/run.py
rikki/appium/__init__.py
rikki/appium/android.py
rikki/appium/common.py
rikki/appium/ios.py
rikki/behave/__init__.py
rikki/behave/context.py
rikki/behave/steps/__init__.py
rikki/behave/steps/proxy.py
rikki/behave/steps/user.py
rikki/behave/steps/utils.py
rikki/mitmproxy/__init__.py
rikki/mitmproxy/delegate_accumulate.py
rikki/mitmproxy/delegate_delay.py
rikki/mitmproxy/delegate_replace.py
rikki/mitmproxy/log_event_interceptor.py
rikki/mitmproxy/model.py
rikki/mitmproxy/plugin.py
rikki/mitmproxy/util.py
rikki/mitmproxy/delgate/__init__.py
rikki/mitmproxy/delgate/dump.py
rikki/template/__init__.py
rikki/template/behave_ini_file.py
rikki/template/environment.py
rikki/template/feature.py
rikki/template/run_file.py
rikki/template/template.py
rikki/tools/__init__.py
rikki/tools/main.py
test/__init__.py
test/rikki/__init__.py
test/rikki/behave/__init__.py
test/rikki/behave/steps/__init__.py
test/rikki/behave/steps/test_utils.py
test/rikki/mitmproxy/__init__.py
test/rikki/mitmproxy/test_accumulate.py
test/rikki/mitmproxy/test_delay.py
test/rikki/mitmproxy/test_filter.py
test/rikki/mitmproxy/test_log_event_interceptor.py
test/rikki/mitmproxy/test_replacement.py
test/rikki/mitmproxy/utils.py
test/rikki/mitmproxy/delegate/__init__.py
test/rikki/mitmproxy/delegate/test_dump.py
rikki-0.0.49.dist-info/METADATA
rikki-0.0.49.dist-info/WHEEL
rikki-0.0.49.dist-info/entry_points.txt
rikki-0.0.49.dist-info/top_level.txt
rikki-0.0.49.dist-info/RECORD
