Metadata-Version: 2.1
Name: rikki
Version: 0.0.49
Summary: A small runner script which allows to run behaviour tests backed by proxy
Home-page: https://github.com/yamsergey/rikki
Author: Sergey Yamshchikov
Author-email: yamsergey@gmail.com
License: UNKNOWN
Platform: UNKNOWN
Classifier: Programming Language :: Python :: 3
Classifier: License :: OSI Approved :: MIT License
Classifier: Operating System :: OS Independent
Requires-Python: >=3.6
Requires-Dist: allure-behave (>=2.8.5)
Requires-Dist: allure-python-commons (>=2.8.5)
Requires-Dist: Appium-Python-Client (>=0.47)
Requires-Dist: behave (>=1.2.6)
Requires-Dist: mitmproxy (>=4.0.4)
Requires-Dist: selenium (>=3.141.0)
Requires-Dist: deepdiff (>=4.0.7)
